aws_cdk/lambda_layer_kubectl_v24/__init__.py
aws_cdk/lambda_layer_kubectl_v24/py.typed
aws_cdk/lambda_layer_kubectl_v24/_jsii/__init__.py
aws_cdk/lambda_layer_kubectl_v24/_jsii/lambda-layer-kubectl-v24@2.0.242.jsii.tgz
aws_cdk.lambda_layer_kubectl_v24-2.0.242.dist-info/LICENSE
aws_cdk.lambda_layer_kubectl_v24-2.0.242.dist-info/METADATA
aws_cdk.lambda_layer_kubectl_v24-2.0.242.dist-info/NOTICE
aws_cdk.lambda_layer_kubectl_v24-2.0.242.dist-info/WHEEL
aws_cdk.lambda_layer_kubectl_v24-2.0.242.dist-info/top_level.txt
aws_cdk.lambda_layer_kubectl_v24-2.0.242.dist-info/RECORD
